image_quality_analysis-0.1.1.dist-info/licenses/LICENSE
image_quality_checker/__init__.py
image_quality_checker/blur_analysis.py
image_quality_checker/quality.py
image_quality_checker/utils.py
image_quality_analysis-0.1.1.dist-info/METADATA
image_quality_analysis-0.1.1.dist-info/WHEEL
image_quality_analysis-0.1.1.dist-info/top_level.txt
image_quality_analysis-0.1.1.dist-info/RECORD
