Metadata-Version: 2.4
Name: image-quality-analysis
Version: 0.1.1
Summary: A Python package for analyzing image quality.
Author-email: Ateeq Azam <mr.ateeqazam@gmail.com>
License: CC BY-ND
Project-URL: Homepage, https://github.com/semwaqas/image-quality-score
Project-URL: Repository, https://github.com/semwaqas/image-quality-score
Keywords: image processing,image quality,computer vision
License-File: LICENSE
Requires-Dist: opencv-python
Requires-Dist: numpy
Requires-Dist: scipy
Requires-Dist: scikit-learn
Dynamic: license-file
